{
  "id": "admin-web-mvp",
  "name": "admin-web-mvp",
  "title": "Vue 管理端 MVP",
  "description": "",
  "status": "in_progress",
  "dev_type": null,
  "scope": null,
  "package": null,
  "priority": "P2",
  "creator": "lautung",
  "assignee": "lautung",
  "createdAt": "2026-06-21",
  "completedAt": null,
  "branch": null,
  "base_branch": "master",
  "worktree_path": null,
  "commit": null,
  "pr_url": null,
  "subtasks": [],
  "children": [],
  "parent": "06-21-project-completeness-roadmap",
  "relatedFiles": [],
  "notes": "",
  "meta": {}
}